gonioimsoft/__init__.py
gonioimsoft/anglepairs.py
gonioimsoft/arduino_serial.py
gonioimsoft/camera_client.py
gonioimsoft/camera_server.py
gonioimsoft/clientbase.py
gonioimsoft/common.py
gonioimsoft/core.py
gonioimsoft/directories.py
gonioimsoft/imaging_parameters.py
gonioimsoft/libtui.py
gonioimsoft/macro.py
gonioimsoft/make_macro.py
gonioimsoft/motors.py
gonioimsoft/serverbase.py
gonioimsoft/stimulus.py
gonioimsoft/tui.py
gonioimsoft/version.py
gonioimsoft/vio_client.py
gonioimsoft/vio_server.py
gonio_imsoft-0.2.0.dist-info/LICENSE
gonio_imsoft-0.2.0.dist-info/METADATA
gonio_imsoft-0.2.0.dist-info/WHEEL
gonio_imsoft-0.2.0.dist-info/top_level.txt
gonio_imsoft-0.2.0.dist-info/RECORD
