Metadata-Version: 2.1
Name: gonio-imsoft
Version: 0.2.0
Summary: Goniometric imaging software
Home-page: https://github.com/jkemppainen/gonio-imsoft
Author: Joni Kemppainen
Author-email: joni.kemppainen@windowslive.com
Classifier: Programming Language :: Python :: 3
Classifier: License :: OSI Approved :: GNU General Public License v3 (GPLv3) 
Classifier: Operating System :: Microsoft :: Windows
Classifier: Intended Audience :: Science/Research
Classifier: Environment :: Console
Requires-Python: >=3.6
License-File: LICENSE
Requires-Dist: numpy
Requires-Dist: matplotlib
Requires-Dist: tifffile
Requires-Dist: pymmcore
Requires-Dist: nidaqmx
Requires-Dist: pyserial
Requires-Dist: python-biosystfiles
